[
   {
      "prop": "new",
      "title": "Eye Mesh Boat Shoes",
      "price": "$220.00",
      "img": "img/page/prod1.jpg"
   },
   {
      "prop": "new",
      "title": "Eye Mesh Boat Shoes",
      "price": "$220.00",
      "img": "img/page/prod2.jpg"
   },
   {
      "prop": "new",
      "title": "Eye Mesh Boat Shoes",
      "price": "$220.00",
      "img": "img/page/prod3.jpg"
   },
   {
      "prop": "new",
      "title": "Eye Mesh Boat Shoes",
      "price": "$220.00",
      "img": "img/page/prod4.jpg"
   },
   {
      "prop": "new",
      "title": "Eye Mesh Boat Shoes",
      "price": "$220.00",
      "img": "img/page/prod5.jpg"
   }
]